odoo/addons/project_task_timesheet_report/README.rst
odoo/addons/project_task_timesheet_report/__init__.py
odoo/addons/project_task_timesheet_report/__manifest__.py
odoo/addons/project_task_timesheet_report/i18n/es_MX.po
odoo/addons/project_task_timesheet_report/i18n/project_task_timesheet_report.pot
odoo/addons/project_task_timesheet_report/readme/CONTRIBUTORS.rst
odoo/addons/project_task_timesheet_report/readme/DESCRIPTION.rst
odoo/addons/project_task_timesheet_report/readme/USAGE.rst
odoo/addons/project_task_timesheet_report/static/description/icon.png
odoo/addons/project_task_timesheet_report/static/description/index.html
odoo/addons/project_task_timesheet_report/views/project_task_chatter_report.xml
odoo/addons/project_task_timesheet_report/views/project_task_report.xml
odoo13_addon_project_task_timesheet_report-13.0.1.0.1.dev6.dist-info/METADATA
odoo13_addon_project_task_timesheet_report-13.0.1.0.1.dev6.dist-info/WHEEL
odoo13_addon_project_task_timesheet_report-13.0.1.0.1.dev6.dist-info/top_level.txt
odoo13_addon_project_task_timesheet_report-13.0.1.0.1.dev6.dist-info/RECORD
